{
    "title": {
        "text": "[오!클릭] 프란치스코 교황은 '태권도 10단'…명예 단증 수여.", 
        "NE": ""
    }, 
    "metaInfo": {
        "field": "뉴스3", 
        "num_sent": 9, 
        "num_word": 105
    }, 
    "sentence": [
        {
            "id": 0, 
            "text": "[오!클릭] 프란치스코 교황은 '태권도 10단'…명예 단증 수여.", 
            "morp": [
                {"id": 0, "lemma": "[", "type": "SS", "position": 0, "weight": 1}, 
                {"id": 1, "lemma": "오", "type": "IC", "position": 1, "weight": 0.0001}, 
                {"id": 2, "lemma": "!", "type": "SF", "position": 4, "weight": 1}, 
                {"id": 3, "lemma": "클릭", "type": "NNG", "position": 5, "weight": 0.9}, 
                {"id": 4, "lemma": "]", "type": "SS", "position": 11, "weight": 1}, 
                {"id": 5, "lemma": "프란치스코", "type": "NNP", "position": 13, "weight": 0.75}, 
                {"id": 6, "lemma": "교황", "type": "NNG", "position": 29, "weight": 0.9}, 
                {"id": 7, "lemma": "은", "type": "JX", "position": 35, "weight": 0.0449928}, 
                {"id": 8, "lemma": "'", "type": "SS", "position": 39, "weight": 1}, 
                {"id": 9, "lemma": "태권", "type": "NNG", "position": 40, "weight": 0.171429}, 
                {"id": 10, "lemma": "도", "type": "JX", "position": 46, "weight": 0.0676272}, 
                {"id": 11, "lemma": "10", "type": "SN", "position": 50, "weight": 1}, 
                {"id": 12, "lemma": "단", "type": "NNG", "position": 52, "weight": 0.0192759}, 
                {"id": 13, "lemma": "'", "type": "SS", "position": 55, "weight": 1}, 
                {"id": 14, "lemma": "…", "type": "SE", "position": 56, "weight": 1}, 
                {"id": 15, "lemma": "명예", "type": "NNG", "position": 59, "weight": 0.9}, 
                {"id": 16, "lemma": "단증", "type": "NNG", "position": 66, "weight": 0}, 
                {"id": 17, "lemma": "수여", "type": "NNG", "position": 73, "weight": 0.9}, 
                {"id": 18, "lemma": ".", "type": "SF", "position": 79, "weight": 1}
            ], 
            "word": [
                {"id": 0, "text": "[오!클릭]", "type": "", "begin": 0, "end": 4}, 
                {"id": 1, "text": "프란치스코", "type": "", "begin": 5, "end": 5}, 
                {"id": 2, "text": "교황은", "type": "", "begin": 6, "end": 7}, 
                {"id": 3, "text": "'태권도", "type": "", "begin": 8, "end": 10}, 
                {"id": 4, "text": "10단'…명예", "type": "", "begin": 11, "end": 15}, 
                {"id": 5, "text": "단증", "type": "", "begin": 16, "end": 16}, 
                {"id": 6, "text": "수여.", "type": "", "begin": 17, "end": 18}
            ], 
            "NE": [
                {"id": 0, "text": "오!클릭", "type": "AFW_MUSIC", "begin": 1, "end": 3, "weight": 0.620375, "common_noun": 0}, 
                {"id": 1, "text": "프란치스코", "type": "PS_NAME", "begin": 5, "end": 5, "weight": 0.380995, "common_noun": 0}, 
                {"id": 2, "text": "교황", "type": "CV_POSITION", "begin": 6, "end": 6, "weight": 0.62788, "common_noun": 0}, 
                {"id": 3, "text": "태권도", "type": "CV_SPORTS", "begin": 9, "end": 10, "weight": 0.633912, "common_noun": 0}, 
                {"id": 4, "text": "10단", "type": "QT_ORDER", "begin": 11, "end": 12, "weight": 0.465298, "common_noun": 0}
            ], 
            "dependency": [
                {"id": 0, "text": "[오!클릭]", "head": 6, "label": "IP", "mod": [], "weight": 0.176645}, 
                {"id": 1, "text": "프란치스코", "head": 2, "label": "NP", "mod": [], "weight": 0.758268}, 
                {"id": 2, "text": "교황은", "head": 6, "label": "NP_SBJ", "mod": [1], "weight": 0.868979}, 
                {"id": 3, "text": "'태권도", "head": 4, "label": "NP", "mod": [], "weight": 0.369555}, 
                {"id": 4, "text": "10단'…명예", "head": 6, "label": "NP", "mod": [3], "weight": 0.534052}, 
                {"id": 5, "text": "단증", "head": 6, "label": "NP", "mod": [], "weight": 0.786305}, 
                {"id": 6, "text": "수여.", "head": -1, "label": "NP", "mod": [0, 2, 4, 5], "weight": 0.0158045}
            ], 
            "phrase_dependency": [
                {"id": 0, "label": "IP", "text": "[오!클릭]", "begin": 0, "end": 0, "key_begin": 0, "head_phrase": 2, "sub_phrase": [], "weight": 0, "element": []}, 
                {"id": 1, "label": "NP_SBJ", "text": "프란치스코 교황은", "begin": 1, "end": 2, "key_begin": 1, "head_phrase": 2, "sub_phrase": [], "weight": 0, "element": []}, 
                {"id": 2, "label": "S", "text": "P#0@IP클릭] P#1@SBJ은 '태권도 10단'…명예 단증 수여.", "begin": 0, "end": 6, "key_begin": 3, "head_phrase": -1, "sub_phrase": [0, 1], "weight": 0, "element": []}
            ], 
            "SRL": [], 
            "ZA": []
        }, 
        {
            "id": 1, 
            "text": "바티칸에서는 조금 특별한 태권도 단증 수여식이 열렸습니다.", 
            "morp": [
                {"id": 0, "lemma": "바티칸", "type": "NNP", "position": 80, "weight": 0.0829208}, 
                {"id": 1, "lemma": "에서", "type": "JKB", "position": 89, "weight": 0.0823859}, 
                {"id": 2, "lemma": "는", "type": "JX", "position": 95, "weight": 0.0387928}, 
                {"id": 3, "lemma": "조금", "type": "MAG", "position": 99, "weight": 0.0915743}, 
                {"id": 4, "lemma": "특별", "type": "NNG", "position": 106, "weight": 0.9}, 
                {"id": 5, "lemma": "하", "type": "XSA", "position": 112, "weight": 0.0001}, 
                {"id": 6, "lemma": "ㄴ", "type": "ETM", "position": 112, "weight": 0.488779}, 
                {"id": 7, "lemma": "태권", "type": "NNG", "position": 116, "weight": 0.564721}, 
                {"id": 8, "lemma": "도", "type": "XSN", "position": 122, "weight": 0.0001}, 
                {"id": 9, "lemma": "단증", "type": "NNG", "position": 126, "weight": 0}, 
                {"id": 10, "lemma": "수여", "type": "NNG", "position": 133, "weight": 0.9}, 
                {"id": 11, "lemma": "식", "type": "XSN", "position": 139, "weight": 0.0146035}, 
                {"id": 12, "lemma": "이", "type": "JKS", "position": 142, "weight": 0.0731805}, 
                {"id": 13, "lemma": "열리", "type": "VV", "position": 146, "weight": 0.9}, 
                {"id": 14, "lemma": "었", "type": "EP", "position": 149, "weight": 0.9}, 
                {"id": 15, "lemma": "습니다", "type": "EF", "position": 152, "weight": 0.660908}, 
                {"id": 16, "lemma": ".", "type": "SF", "position": 161, "weight": 1}
            ], 
            "word": [
                {"id": 0, "text": "바티칸에서는", "type": "", "begin": 0, "end": 2}, 
                {"id": 1, "text": "조금", "type": "", "begin": 3, "end": 3}, 
                {"id": 2, "text": "특별한", "type": "", "begin": 4, "end": 6}, 
                {"id": 3, "text": "태권도", "type": "", "begin": 7, "end": 8}, 
                {"id": 4, "text": "단증", "type": "", "begin": 9, "end": 9}, 
                {"id": 5, "text": "수여식이", "type": "", "begin": 10, "end": 12}, 
                {"id": 6, "text": "열렸습니다.", "type": "", "begin": 13, "end": 16}
            ], 
            "NE": [
                {"id": 0, "text": "바티칸", "type": "LCP_COUNTRY", "begin": 0, "end": 0, "weight": 0.475509, "common_noun": 0}, 
                {"id": 1, "text": "태권도", "type": "CV_SPORTS", "begin": 7, "end": 8, "weight": 0.810444, "common_noun": 0}
            ], 
            "dependency": [
                {"id": 0, "text": "바티칸에서는", "head": 6, "label": "NP_AJT", "mod": [], "weight": 0.759539}, 
                {"id": 1, "text": "조금", "head": 2, "label": "AP", "mod": [], "weight": 0.0780859}, 
                {"id": 2, "text": "특별한", "head": 5, "label": "VP_MOD", "mod": [1], "weight": 0.707864}, 
                {"id": 3, "text": "태권도", "head": 4, "label": "NP", "mod": [], "weight": 0.172001}, 
                {"id": 4, "text": "단증", "head": 5, "label": "NP", "mod": [3], "weight": 0.24527}, 
                {"id": 5, "text": "수여식이", "head": 6, "label": "NP_SBJ", "mod": [2, 4], "weight": 0.827087}, 
                {"id": 6, "text": "열렸습니다.", "head": -1, "label": "VP", "mod": [0, 5], "weight": 0.00124883}
            ], 
            "phrase_dependency": [
                {"id": 0, "label": "NP_AJT", "text": "바티칸에서는", "begin": 0, "end": 0, "key_begin": 0, "head_phrase": 4, "sub_phrase": [], "weight": 0, "element": []}, 
                {"id": 1, "label": "AP", "text": "조금", "begin": 1, "end": 1, "key_begin": 1, "head_phrase": 2, "sub_phrase": [], "weight": 0, "element": []}, 
                {"id": 2, "label": "VP_MOD", "text": "P#1@AP조금 특별한", "begin": 1, "end": 2, "key_begin": 2, "head_phrase": 3, "sub_phrase": [1], "weight": 0, "element": []}, 
                {"id": 3, "label": "NP_SBJ", "text": "P#2@MODㄴ 태권도 단증 수여식이", "begin": 1, "end": 5, "key_begin": 3, "head_phrase": 4, "sub_phrase": [2], "weight": 0, "element": []}, 
                {"id": 4, "label": "S", "text": "P#0@AJT는 P#3@SBJ이 열렸습니다.", "begin": 0, "end": 6, "key_begin": 6, "head_phrase": -1, "sub_phrase": [0, 3], "weight": 0, "element": []}
            ], 
            "SRL": [
                {"verb": "특별", "sense": 1, "word_id": 2, "weight": 0.331881, "argument": [
                    {"type": "ARGM-EXT", "word_id": 1, "text": "조금", "weight": 0.328474}, 
                    {"type": "ARG1", "word_id": 5, "text": "태권도 단증 수여식", "weight": 0.335288}
                ]}, 
                {"verb": "열리", "sense": 1, "word_id": 6, "weight": 0.414614, "argument": [
                    {"type": "ARGM-LOC", "word_id": 0, "text": "바티칸", "weight": 0.29705}, 
                    {"type": "ARG1", "word_id": 5, "text": "태권도 단증 수여식", "weight": 0.532178}
                ]}
            ], 
            "ZA": []
        }, 
        {
            "id": 2, 
            "text": "비록 '명예' 단증이라고 해도 무려 10단인데요, 이 명예단증의 주인공은 바로 프란치스코 교황이었습니다.", 
            "morp": [
                {"id": 0, "lemma": "비록", "type": "MAG", "position": 162, "weight": 0.0653953}, 
                {"id": 1, "lemma": "'", "type": "SS", "position": 169, "weight": 1}, 
                {"id": 2, "lemma": "명예", "type": "NNG", "position": 170, "weight": 0.9}, 
                {"id": 3, "lemma": "'", "type": "SS", "position": 176, "weight": 1}, 
                {"id": 4, "lemma": "단증", "type": "NNG", "position": 178, "weight": 0}, 
                {"id": 5, "lemma": "이", "type": "VCP", "position": 184, "weight": 0.0177525}, 
                {"id": 6, "lemma": "라고", "type": "EC", "position": 187, "weight": 0.204147}, 
                {"id": 7, "lemma": "하", "type": "VV", "position": 194, "weight": 0.140183}, 
                {"id": 8, "lemma": "어도", "type": "EC", "position": 194, "weight": 0.430707}, 
                {"id": 9, "lemma": "무려", "type": "MAG", "position": 201, "weight": 0.0473235}, 
                {"id": 10, "lemma": "10", "type": "SN", "position": 208, "weight": 1}, 
                {"id": 11, "lemma": "단", "type": "NNB", "position": 210, "weight": 0.00866069}, 
                {"id": 12, "lemma": "이", "type": "VCP", "position": 213, "weight": 0.0607843}, 
                {"id": 13, "lemma": "ㄴ데", "type": "EF", "position": 213, "weight": 0.0631875}, 
                {"id": 14, "lemma": "요", "type": "JX", "position": 219, "weight": 0.00618742}, 
                {"id": 15, "lemma": ",", "type": "SP", "position": 222, "weight": 1}, 
                {"id": 16, "lemma": "이", "type": "MM", "position": 224, "weight": 0.0017249}, 
                {"id": 17, "lemma": "명예단증", "type": "NNG", "position": 228, "weight": 0}, 
                {"id": 18, "lemma": "의", "type": "JKG", "position": 240, "weight": 0.0694213}, 
                {"id": 19, "lemma": "주인", "type": "NNG", "position": 244, "weight": 0.9}, 
                {"id": 20, "lemma": "공", "type": "XSN", "position": 250, "weight": 0.00025927}, 
                {"id": 21, "lemma": "은", "type": "JX", "position": 253, "weight": 0.100393}, 
                {"id": 22, "lemma": "바로", "type": "MAG", "position": 257, "weight": 0.127006}, 
                {"id": 23, "lemma": "프란치스코", "type": "NNP", "position": 264, "weight": 0.75}, 
                {"id": 24, "lemma": "교황", "type": "NNG", "position": 280, "weight": 0.9}, 
                {"id": 25, "lemma": "이", "type": "VCP", "position": 286, "weight": 0.0177525}, 
                {"id": 26, "lemma": "었", "type": "EP", "position": 289, "weight": 0.9}, 
                {"id": 27, "lemma": "습니다", "type": "EF", "position": 292, "weight": 0.660908}, 
                {"id": 28, "lemma": ".", "type": "SF", "position": 301, "weight": 1}
            ], 
            "word": [
                {"id": 0, "text": "비록", "type": "", "begin": 0, "end": 0}, 
                {"id": 1, "text": "'명예'", "type": "", "begin": 1, "end": 3}, 
                {"id": 2, "text": "단증이라고", "type": "", "begin": 4, "end": 6}, 
                {"id": 3, "text": "해도", "type": "", "begin": 7, "end": 8}, 
                {"id": 4, "text": "무려", "type": "", "begin": 9, "end": 9}, 
                {"id": 5, "text": "10단인데요,", "type": "", "begin": 10, "end": 15}, 
                {"id": 6, "text": "이", "type": "", "begin": 16, "end": 16}, 
                {"id": 7, "text": "명예단증의", "type": "", "begin": 17, "end": 18}, 
                {"id": 8, "text": "주인공은", "type": "", "begin": 19, "end": 21}, 
                {"id": 9, "text": "바로", "type": "", "begin": 22, "end": 22}, 
                {"id": 10, "text": "프란치스코", "type": "", "begin": 23, "end": 23}, 
                {"id": 11, "text": "교황이었습니다.", "type": "", "begin": 24, "end": 28}
            ], 
            "NE": [
                {"id": 0, "text": "10단", "type": "QT_ORDER", "begin": 10, "end": 11, "weight": 0.556726, "common_noun": 0}, 
                {"id": 1, "text": "주인공", "type": "CV_POSITION", "begin": 19, "end": 20, "weight": 0.474335, "common_noun": 0}, 
                {"id": 2, "text": "프란치스코", "type": "PS_NAME", "begin": 23, "end": 23, "weight": 0.328277, "common_noun": 0}, 
                {"id": 3, "text": "교황", "type": "CV_POSITION", "begin": 24, "end": 24, "weight": 0.774416, "common_noun": 0}
            ], 
            "dependency": [
                {"id": 0, "text": "비록", "head": 2, "label": "AP", "mod": [], "weight": 0.676765}, 
                {"id": 1, "text": "'명예'", "head": 2, "label": "NP", "mod": [], "weight": 0.620904}, 
                {"id": 2, "text": "단증이라고", "head": 3, "label": "VNP_CMP", "mod": [0, 1], "weight": 0.516587}, 
                {"id": 3, "text": "해도", "head": 11, "label": "VP", "mod": [2], "weight": 0.875691}, 
                {"id": 4, "text": "무려", "head": 5, "label": "AP", "mod": [], "weight": 0.300144}, 
                {"id": 5, "text": "10단인데요,", "head": 11, "label": "NP_SBJ", "mod": [4], "weight": 0.274489}, 
                {"id": 6, "text": "이", "head": 7, "label": "DP", "mod": [], "weight": 0.720492}, 
                {"id": 7, "text": "명예단증의", "head": 8, "label": "NP_MOD", "mod": [6], "weight": 0.707165}, 
                {"id": 8, "text": "주인공은", "head": 11, "label": "NP_SBJ", "mod": [7], "weight": 0.854848}, 
                {"id": 9, "text": "바로", "head": 11, "label": "AP", "mod": [], "weight": 0.840152}, 
                {"id": 10, "text": "프란치스코", "head": 11, "label": "NP", "mod": [], "weight": 0.765178}, 
                {"id": 11, "text": "교황이었습니다.", "head": -1, "label": "VNP", "mod": [3, 5, 8, 9, 10], "weight": 0.00370749}
            ], 
            "phrase_dependency": [
                {"id": 0, "label": "VNP_CMP", "text": "비록 '명예' 단증이라고", "begin": 0, "end": 2, "key_begin": 0, "head_phrase": 1, "sub_phrase": [], "weight": 0, "element": []}, 
                {"id": 1, "label": "VP", "text": "P#0@CMP라고 해도", "begin": 0, "end": 3, "key_begin": 3, "head_phrase": 4, "sub_phrase": [0], "weight": 0, "element": []}, 
                {"id": 2, "label": "NP_SBJ", "text": "무려 10단인데요,", "begin": 4, "end": 5, "key_begin": 4, "head_phrase": 4, "sub_phrase": [], "weight": 0, "element": []}, 
                {"id": 3, "label": "NP_SBJ", "text": "이 명예단증의 주인공은", "begin": 6, "end": 8, "key_begin": 6, "head_phrase": 4, "sub_phrase": [], "weight": 0, "element": []}, 
                {"id": 4, "label": "S", "text": "P#1@VP어도 P#2@SBJ요, P#3@SBJ은 바로 프란치스코 교황이었습니다.", "begin": 0, "end": 11, "key_begin": 9, "head_phrase": -1, "sub_phrase": [1, 2, 3], "weight": 0, "element": [
                    {"text": "바로 프란치스코 교황", "label": "NP", "begin": 22, "end": 24, "ne_type": ""}, 
                    {"text": "이었습니다.", "label": "VP", "begin": 25, "end": 28, "ne_type": ""}
                ]}
            ], 
            "SRL": [
                {"verb": "하", "sense": 2, "word_id": 3, "weight": 0.30215, "argument": [
                    {"type": "ARG2", "word_id": 2, "text": "비록 '명예' 단증이라고", "weight": 1}
                ]}
            ], 
            "ZA": [
                {"id": 0, "type": "s", "head_wid": 2, "ant_sid": -1, "ant_wid": -1, "ant_is_title": 0, "weight": 1.01}
            ]
        }, 
        {
            "id": 3, 
            "text": "<오! 클릭> 세 번째 검색어는 '태권도 10단'입니다.", 
            "morp": [
                {"id": 0, "lemma": "<", "type": "SS", "position": 302, "weight": 1}, 
                {"id": 1, "lemma": "오", "type": "IC", "position": 303, "weight": 0.0001}, 
                {"id": 2, "lemma": "!", "type": "SF", "position": 306, "weight": 1}, 
                {"id": 3, "lemma": "클릭", "type": "NNG", "position": 308, "weight": 0.9}, 
                {"id": 4, "lemma": ">", "type": "SS", "position": 314, "weight": 1}, 
                {"id": 5, "lemma": "세", "type": "MM", "position": 316, "weight": 0.00349237}, 
                {"id": 6, "lemma": "번째", "type": "NNB", "position": 320, "weight": 0.18051}, 
                {"id": 7, "lemma": "검색", "type": "NNG", "position": 327, "weight": 0.9}, 
                {"id": 8, "lemma": "어", "type": "XSN", "position": 333, "weight": 0.0001}, 
                {"id": 9, "lemma": "는", "type": "JX", "position": 336, "weight": 0.0641645}, 
                {"id": 10, "lemma": "'", "type": "SS", "position": 340, "weight": 1}, 
                {"id": 11, "lemma": "태권", "type": "NNG", "position": 341, "weight": 0.171429}, 
                {"id": 12, "lemma": "도", "type": "JX", "position": 347, "weight": 0.0676272}, 
                {"id": 13, "lemma": "10", "type": "SN", "position": 351, "weight": 1}, 
                {"id": 14, "lemma": "단", "type": "NNG", "position": 353, "weight": 0.0192759}, 
                {"id": 15, "lemma": "'", "type": "SS", "position": 356, "weight": 1}, 
                {"id": 16, "lemma": "이", "type": "VCP", "position": 357, "weight": 0.00747344}, 
                {"id": 17, "lemma": "ㅂ니다", "type": "EF", "position": 357, "weight": 0.36174}, 
                {"id": 18, "lemma": ".", "type": "SF", "position": 366, "weight": 1}
            ], 
            "word": [
                {"id": 0, "text": "<오!", "type": "", "begin": 0, "end": 2}, 
                {"id": 1, "text": "클릭>", "type": "", "begin": 3, "end": 4}, 
                {"id": 2, "text": "세", "type": "", "begin": 5, "end": 5}, 
                {"id": 3, "text": "번째", "type": "", "begin": 6, "end": 6}, 
                {"id": 4, "text": "검색어는", "type": "", "begin": 7, "end": 9}, 
                {"id": 5, "text": "'태권도", "type": "", "begin": 10, "end": 12}, 
                {"id": 6, "text": "10단'입니다.", "type": "", "begin": 13, "end": 18}
            ], 
            "NE": [
                {"id": 0, "text": "오! 클릭", "type": "AFW_MUSIC", "begin": 1, "end": 3, "weight": 0.785435, "common_noun": 0}, 
                {"id": 1, "text": "세 번째", "type": "QT_ORDER", "begin": 5, "end": 6, "weight": 0.831927, "common_noun": 0}, 
                {"id": 2, "text": "태권도", "type": "CV_SPORTS", "begin": 11, "end": 12, "weight": 0.625937, "common_noun": 0}, 
                {"id": 3, "text": "10단", "type": "QT_ORDER", "begin": 13, "end": 14, "weight": 0.554544, "common_noun": 0}
            ], 
            "dependency": [
                {"id": 0, "text": "<오!", "head": 1, "label": "IP", "mod": [], "weight": 0.287751}, 
                {"id": 1, "text": "클릭>", "head": 6, "label": "NP", "mod": [0], "weight": 0.558006}, 
                {"id": 2, "text": "세", "head": 3, "label": "DP", "mod": [], "weight": 0.744404}, 
                {"id": 3, "text": "번째", "head": 4, "label": "NP", "mod": [2], "weight": 0.566443}, 
                {"id": 4, "text": "검색어는", "head": 6, "label": "NP_SBJ", "mod": [3], "weight": 0.821488}, 
                {"id": 5, "text": "'태권도", "head": 6, "label": "NP_SBJ", "mod": [], "weight": 0.578888}, 
                {"id": 6, "text": "10단'입니다.", "head": -1, "label": "VNP", "mod": [1, 4, 5], "weight": 0.00482223}
            ], 
            "phrase_dependency": [
                {"id": 0, "label": "NP", "text": "<오! 클릭>", "begin": 0, "end": 1, "key_begin": 0, "head_phrase": 2, "sub_phrase": [], "weight": 0, "element": []}, 
                {"id": 1, "label": "NP_SBJ", "text": "세 번째 검색어는", "begin": 2, "end": 4, "key_begin": 2, "head_phrase": 2, "sub_phrase": [], "weight": 0, "element": []}, 
                {"id": 2, "label": "S", "text": "P#0@NP클릭> P#1@SBJ는 '태권도 10단'입니다.", "begin": 0, "end": 6, "key_begin": 5, "head_phrase": -1, "sub_phrase": [0, 1], "weight": 0, "element": [
                    {"text": "'태권도 10단'", "label": "NP", "begin": 10, "end": 15, "ne_type": ""}, 
                    {"text": "입니다.", "label": "VP", "begin": 16, "end": 18, "ne_type": ""}
                ]}
            ], 
            "SRL": [], 
            "ZA": []
        }, 
        {
            "id": 4, 
            "text": "세계태권도연맹은 어제(10일) 프란치스코 교황에게 태권도 명예 10단증을 수여했습니다.", 
            "morp": [
                {"id": 0, "lemma": "세계", "type": "NNG", "position": 367, "weight": 0.9}, 
                {"id": 1, "lemma": "태권", "type": "NNP", "position": 373, "weight": 0.00101479}, 
                {"id": 2, "lemma": "도", "type": "XSN", "position": 379, "weight": 0.0001}, 
                {"id": 3, "lemma": "연맹", "type": "NNG", "position": 382, "weight": 0.9}, 
                {"id": 4, "lemma": "은", "type": "JX", "position": 388, "weight": 0.0449928}, 
                {"id": 5, "lemma": "어제", "type": "NNG", "position": 392, "weight": 0.197095}, 
                {"id": 6, "lemma": "(", "type": "SS", "position": 398, "weight": 1}, 
                {"id": 7, "lemma": "10", "type": "SN", "position": 399, "weight": 1}, 
                {"id": 8, "lemma": "일", "type": "NNB", "position": 401, "weight": 0.126777}, 
                {"id": 9, "lemma": ")", "type": "SS", "position": 404, "weight": 1}, 
                {"id": 10, "lemma": "프란치스코", "type": "NNP", "position": 406, "weight": 0.75}, 
                {"id": 11, "lemma": "교황", "type": "NNG", "position": 422, "weight": 0.9}, 
                {"id": 12, "lemma": "에게", "type": "JKB", "position": 428, "weight": 0.153356}, 
                {"id": 13, "lemma": "태권", "type": "NNG", "position": 435, "weight": 0.178325}, 
                {"id": 14, "lemma": "도", "type": "XSN", "position": 441, "weight": 0.0001}, 
                {"id": 15, "lemma": "명예", "type": "NNG", "position": 445, "weight": 0.9}, 
                {"id": 16, "lemma": "10", "type": "SN", "position": 452, "weight": 1}, 
                {"id": 17, "lemma": "단증", "type": "NNG", "position": 454, "weight": 0}, 
                {"id": 18, "lemma": "을", "type": "JKO", "position": 460, "weight": 0.129611}, 
                {"id": 19, "lemma": "수여", "type": "NNG", "position": 464, "weight": 0.9}, 
                {"id": 20, "lemma": "하", "type": "XSV", "position": 470, "weight": 0.0001}, 
                {"id": 21, "lemma": "었", "type": "EP", "position": 470, "weight": 0.9}, 
                {"id": 22, "lemma": "습니다", "type": "EF", "position": 473, "weight": 0.660908}, 
                {"id": 23, "lemma": ".", "type": "SF", "position": 482, "weight": 1}
            ], 
            "word": [
                {"id": 0, "text": "세계태권도연맹은", "type": "", "begin": 0, "end": 4}, 
                {"id": 1, "text": "어제(10일)", "type": "", "begin": 5, "end": 9}, 
                {"id": 2, "text": "프란치스코", "type": "", "begin": 10, "end": 10}, 
                {"id": 3, "text": "교황에게", "type": "", "begin": 11, "end": 12}, 
                {"id": 4, "text": "태권도", "type": "", "begin": 13, "end": 14}, 
                {"id": 5, "text": "명예", "type": "", "begin": 15, "end": 15}, 
                {"id": 6, "text": "10단증을", "type": "", "begin": 16, "end": 18}, 
                {"id": 7, "text": "수여했습니다.", "type": "", "begin": 19, "end": 23}
            ], 
            "NE": [
                {"id": 0, "text": "세계태권도연맹", "type": "OGG_SPORTS", "begin": 0, "end": 3, "weight": 0.913435, "common_noun": 0}, 
                {"id": 1, "text": "어제", "type": "DT_DAY", "begin": 5, "end": 5, "weight": 0.496337, "common_noun": 0}, 
                {"id": 2, "text": "10일", "type": "DT_DAY", "begin": 7, "end": 8, "weight": 0.809594, "common_noun": 0}, 
                {"id": 3, "text": "프란치스코", "type": "PS_NAME", "begin": 10, "end": 10, "weight": 0.489058, "common_noun": 0}, 
                {"id": 4, "text": "교황", "type": "CV_POSITION", "begin": 11, "end": 11, "weight": 0.817687, "common_noun": 0}, 
                {"id": 5, "text": "태권도", "type": "CV_SPORTS", "begin": 13, "end": 14, "weight": 0.79765, "common_noun": 0}, 
                {"id": 6, "text": "10단증", "type": "QT_COUNT", "begin": 16, "end": 17, "weight": 0.438543, "common_noun": 0}
            ], 
            "dependency": [
                {"id": 0, "text": "세계태권도연맹은", "head": 7, "label": "NP_SBJ", "mod": [], "weight": 0.744818}, 
                {"id": 1, "text": "어제(10일)", "head": 7, "label": "NP_AJT", "mod": [], "weight": 0.611667}, 
                {"id": 2, "text": "프란치스코", "head": 3, "label": "NP", "mod": [], "weight": 0.787618}, 
                {"id": 3, "text": "교황에게", "head": 7, "label": "NP_AJT", "mod": [2], "weight": 0.84701}, 
                {"id": 4, "text": "태권도", "head": 5, "label": "NP", "mod": [], "weight": 0.288011}, 
                {"id": 5, "text": "명예", "head": 6, "label": "NP", "mod": [4], "weight": 0.526693}, 
                {"id": 6, "text": "10단증을", "head": 7, "label": "NP_OBJ", "mod": [5], "weight": 0.768194}, 
                {"id": 7, "text": "수여했습니다.", "head": -1, "label": "VP", "mod": [0, 1, 3, 6], "weight": 0.030767}
            ], 
            "phrase_dependency": [
                {"id": 0, "label": "NP_SBJ", "text": "세계태권도연맹은", "begin": 0, "end": 0, "key_begin": 0, "head_phrase": 4, "sub_phrase": [], "weight": 0, "element": []}, 
                {"id": 1, "label": "NP_AJT", "text": "어제(10일)", "begin": 1, "end": 1, "key_begin": 1, "head_phrase": 4, "sub_phrase": [], "weight": 0, "element": []}, 
                {"id": 2, "label": "NP_AJT", "text": "프란치스코 교황에게", "begin": 2, "end": 3, "key_begin": 2, "head_phrase": 4, "sub_phrase": [], "weight": 0, "element": []}, 
                {"id": 3, "label": "NP_OBJ", "text": "태권도 명예 10단증을", "begin": 4, "end": 6, "key_begin": 4, "head_phrase": 4, "sub_phrase": [], "weight": 0, "element": []}, 
                {"id": 4, "label": "S", "text": "P#0@SBJ은 P#1@AJT일) P#2@AJT에게 P#3@OBJ을 수여했습니다.", "begin": 0, "end": 7, "key_begin": 7, "head_phrase": -1, "sub_phrase": [0, 1, 2, 3], "weight": 0, "element": []}
            ], 
            "SRL": [
                {"verb": "수여", "sense": 1, "word_id": 7, "weight": 0.239872, "argument": [
                    {"type": "ARG0", "word_id": 0, "text": "세계태권도연맹", "weight": 0.183178}, 
                    {"type": "ARGM-TMP", "word_id": 1, "text": "어제(10일)", "weight": 0.223295}, 
                    {"type": "ARG2", "word_id": 3, "text": "프란치스코 교황", "weight": 0.283714}, 
                    {"type": "ARG1", "word_id": 6, "text": "태권도 명예 10단증", "weight": 0.2693}
                ]}
            ], 
            "ZA": []
        }, 
        {
            "id": 5, 
            "text": "태권도 도복과 검은 띠도 함께 전달됐는데요, 평소 태권도 종주국인 우리나라 가톨릭에 대해 애정을 보여온 프란치스코 교황은 함박웃음을 지은 것으로 전해졌습니다.", 
            "morp": [
                {"id": 0, "lemma": "태권", "type": "NNG", "position": 483, "weight": 0.375384}, 
                {"id": 1, "lemma": "도", "type": "XSN", "position": 489, "weight": 0.0001}, 
                {"id": 2, "lemma": "도복", "type": "NNG", "position": 493, "weight": 0.120336}, 
                {"id": 3, "lemma": "과", "type": "JC", "position": 499, "weight": 0.017569}, 
                {"id": 4, "lemma": "검", "type": "VA", "position": 503, "weight": 0.0228734}, 
                {"id": 5, "lemma": "은", "type": "ETM", "position": 506, "weight": 0.155123}, 
                {"id": 6, "lemma": "띠", "type": "NNG", "position": 510, "weight": 0.111773}, 
                {"id": 7, "lemma": "도", "type": "JX", "position": 513, "weight": 0.0676272}, 
                {"id": 8, "lemma": "함께", "type": "MAG", "position": 517, "weight": 0.9}, 
                {"id": 9, "lemma": "전달", "type": "NNG", "position": 524, "weight": 0.9}, 
                {"id": 10, "lemma": "되", "type": "XSV", "position": 530, "weight": 0.000224177}, 
                {"id": 11, "lemma": "었", "type": "EP", "position": 530, "weight": 0.9}, 
                {"id": 12, "lemma": "는데요", "type": "EC", "position": 533, "weight": 0.0215501}, 
                {"id": 13, "lemma": ",", "type": "SP", "position": 542, "weight": 1}, 
                {"id": 14, "lemma": "평소", "type": "NNG", "position": 544, "weight": 0.9}, 
                {"id": 15, "lemma": "태권", "type": "NNG", "position": 551, "weight": 0.158434}, 
                {"id": 16, "lemma": "도", "type": "XSN", "position": 557, "weight": 0.0001}, 
                {"id": 17, "lemma": "종주", "type": "NNG", "position": 561, "weight": 0.6}, 
                {"id": 18, "lemma": "국", "type": "XSN", "position": 567, "weight": 0.0205107}, 
                {"id": 19, "lemma": "이", "type": "VCP", "position": 570, "weight": 0.0165001}, 
                {"id": 20, "lemma": "ㄴ", "type": "ETM", "position": 570, "weight": 0.220712}, 
                {"id": 21, "lemma": "우리나라", "type": "NNG", "position": 574, "weight": 0.9}, 
                {"id": 22, "lemma": "가톨릭", "type": "NNG", "position": 587, "weight": 0.9}, 
                {"id": 23, "lemma": "에", "type": "JKB", "position": 596, "weight": 0.153364}, 
                {"id": 24, "lemma": "대", "type": "NNG", "position": 600, "weight": 0.0312871}, 
                {"id": 25, "lemma": "하", "type": "XSV", "position": 603, "weight": 0.0001}, 
                {"id": 26, "lemma": "어", "type": "EC", "position": 603, "weight": 0.361326}, 
                {"id": 27, "lemma": "애정", "type": "NNG", "position": 607, "weight": 0.219119}, 
                {"id": 28, "lemma": "을", "type": "JKO", "position": 613, "weight": 0.129611}, 
                {"id": 29, "lemma": "보이", "type": "VV", "position": 617, "weight": 0.776105}, 
                {"id": 30, "lemma": "어", "type": "EC", "position": 620, "weight": 0.41831}, 
                {"id": 31, "lemma": "오", "type": "VX", "position": 620, "weight": 0.0910275}, 
                {"id": 32, "lemma": "ㄴ", "type": "ETM", "position": 620, "weight": 0.302612}, 
                {"id": 33, "lemma": "프란치스코", "type": "NNP", "position": 627, "weight": 0.75}, 
                {"id": 34, "lemma": "교황", "type": "NNG", "position": 643, "weight": 0.9}, 
                {"id": 35, "lemma": "은", "type": "JX", "position": 649, "weight": 0.0449928}, 
                {"id": 36, "lemma": "함박", "type": "NNG", "position": 653, "weight": 0.9}, 
                {"id": 37, "lemma": "웃음", "type": "NNG", "position": 659, "weight": 0.9}, 
                {"id": 38, "lemma": "을", "type": "JKO", "position": 665, "weight": 0.129611}, 
                {"id": 39, "lemma": "짓", "type": "VV", "position": 669, "weight": 0.634592}, 
                {"id": 40, "lemma": "은", "type": "ETM", "position": 672, "weight": 0.109632}, 
                {"id": 41, "lemma": "것", "type": "NNB", "position": 676, "weight": 0.228788}, 
                {"id": 42, "lemma": "으로", "type": "JKB", "position": 679, "weight": 0.135596}, 
                {"id": 43, "lemma": "전하", "type": "VV", "position": 686, "weight": 0.420227}, 
                {"id": 44, "lemma": "어", "type": "EC", "position": 689, "weight": 0.41831}, 
                {"id": 45, "lemma": "지", "type": "VX", "position": 689, "weight": 0.0539764}, 
                {"id": 46, "lemma": "었", "type": "EP", "position": 689, "weight": 0.9}, 
                {"id": 47, "lemma": "습니다", "type": "EF", "position": 695, "weight": 0.660908}, 
                {"id": 48, "lemma": ".", "type": "SF", "position": 704, "weight": 1}
            ], 
            "word": [
                {"id": 0, "text": "태권도", "type": "", "begin": 0, "end": 1}, 
                {"id": 1, "text": "도복과", "type": "", "begin": 2, "end": 3}, 
                {"id": 2, "text": "검은", "type": "", "begin": 4, "end": 5}, 
                {"id": 3, "text": "띠도", "type": "", "begin": 6, "end": 7}, 
                {"id": 4, "text": "함께", "type": "", "begin": 8, "end": 8}, 
                {"id": 5, "text": "전달됐는데요,", "type": "", "begin": 9, "end": 13}, 
                {"id": 6, "text": "평소", "type": "", "begin": 14, "end": 14}, 
                {"id": 7, "text": "태권도", "type": "", "begin": 15, "end": 16}, 
                {"id": 8, "text": "종주국인", "type": "", "begin": 17, "end": 20}, 
                {"id": 9, "text": "우리나라", "type": "", "begin": 21, "end": 21}, 
                {"id": 10, "text": "가톨릭에", "type": "", "begin": 22, "end": 23}, 
                {"id": 11, "text": "대해", "type": "", "begin": 24, "end": 26}, 
                {"id": 12, "text": "애정을", "type": "", "begin": 27, "end": 28}, 
                {"id": 13, "text": "보여온", "type": "", "begin": 29, "end": 32}, 
                {"id": 14, "text": "프란치스코", "type": "", "begin": 33, "end": 33}, 
                {"id": 15, "text": "교황은", "type": "", "begin": 34, "end": 35}, 
                {"id": 16, "text": "함박웃음을", "type": "", "begin": 36, "end": 38}, 
                {"id": 17, "text": "지은", "type": "", "begin": 39, "end": 40}, 
                {"id": 18, "text": "것으로", "type": "", "begin": 41, "end": 42}, 
                {"id": 19, "text": "전해졌습니다.", "type": "", "begin": 43, "end": 48}
            ], 
            "NE": [
                {"id": 0, "text": "태권도", "type": "CV_SPORTS", "begin": 0, "end": 1, "weight": 0.802761, "common_noun": 0}, 
                {"id": 1, "text": "태권도", "type": "CV_SPORTS", "begin": 15, "end": 16, "weight": 0.622694, "common_noun": 0}, 
                {"id": 2, "text": "가톨릭", "type": "OGG_RELIGION", "begin": 22, "end": 22, "weight": 0.328722, "common_noun": 0}, 
                {"id": 3, "text": "프란치스코", "type": "PS_NAME", "begin": 33, "end": 33, "weight": 0.425348, "common_noun": 0}, 
                {"id": 4, "text": "교황", "type": "CV_POSITION", "begin": 34, "end": 34, "weight": 0.639763, "common_noun": 0}
            ], 
            "dependency": [
                {"id": 0, "text": "태권도", "head": 1, "label": "NP", "mod": [], "weight": 0.43287}, 
                {"id": 1, "text": "도복과", "head": 3, "label": "NP_CNJ", "mod": [0], "weight": 0.810298}, 
                {"id": 2, "text": "검은", "head": 3, "label": "VP_MOD", "mod": [], "weight": 0.719082}, 
                {"id": 3, "text": "띠도", "head": 5, "label": "NP_SBJ", "mod": [1, 2], "weight": 0.0575037}, 
                {"id": 4, "text": "함께", "head": 5, "label": "AP", "mod": [], "weight": 0.812834}, 
                {"id": 5, "text": "전달됐는데요,", "head": 19, "label": "VP", "mod": [3, 4], "weight": 0.427385}, 
                {"id": 6, "text": "평소", "head": 7, "label": "NP", "mod": [], "weight": 0.0213803}, 
                {"id": 7, "text": "태권도", "head": 8, "label": "NP", "mod": [6], "weight": 0.567202}, 
                {"id": 8, "text": "종주국인", "head": 10, "label": "VNP_MOD", "mod": [7], "weight": 0.676938}, 
                {"id": 9, "text": "우리나라", "head": 10, "label": "NP", "mod": [], "weight": 0.495544}, 
                {"id": 10, "text": "가톨릭에", "head": 11, "label": "NP_AJT", "mod": [8, 9], "weight": 0.649378}, 
                {"id": 11, "text": "대해", "head": 13, "label": "VP", "mod": [10], "weight": 0.707122}, 
                {"id": 12, "text": "애정을", "head": 13, "label": "NP_OBJ", "mod": [], "weight": 0.739279}, 
                {"id": 13, "text": "보여온", "head": 15, "label": "VP_MOD", "mod": [11, 12], "weight": 0.634645}, 
                {"id": 14, "text": "프란치스코", "head": 15, "label": "NP", "mod": [], "weight": 0.736856}, 
                {"id": 15, "text": "교황은", "head": 19, "label": "NP_SBJ", "mod": [13, 14], "weight": 0.709584}, 
                {"id": 16, "text": "함박웃음을", "head": 17, "label": "NP_OBJ", "mod": [], "weight": 0.7326}, 
                {"id": 17, "text": "지은", "head": 18, "label": "VP_MOD", "mod": [16], "weight": 0.748513}, 
                {"id": 18, "text": "것으로", "head": 19, "label": "NP_AJT", "mod": [17], "weight": 0.783194}, 
                {"id": 19, "text": "전해졌습니다.", "head": -1, "label": "VP", "mod": [5, 15, 18], "weight": 8.06636e-07}
            ], 
            "phrase_dependency": [
                {"id": 0, "label": "NP_SBJ", "text": "태권도 도복과 검은 띠도", "begin": 0, "end": 3, "key_begin": 0, "head_phrase": 2, "sub_phrase": [], "weight": 0, "element": [
                    {"text": "태권도 도복", "label": "NP_SBJ", "begin": 0, "end": 2, "ne_type": ""}, 
                    {"text": "검은 띠", "label": "NP_SBJ", "begin": 4, "end": 6, "ne_type": ""}
                ]}, 
                {"id": 1, "label": "AP", "text": "함께", "begin": 4, "end": 4, "key_begin": 4, "head_phrase": 2, "sub_phrase": [], "weight": 0, "element": []}, 
                {"id": 2, "label": "S", "text": "P#0@SBJ도 P#1@AP함께 전달됐는데요,", "begin": 0, "end": 5, "key_begin": 5, "head_phrase": 12, "sub_phrase": [0, 1], "weight": 0, "element": []}, 
                {"id": 3, "label": "VNP_MOD", "text": "평소 태권도 종주국인", "begin": 6, "end": 8, "key_begin": 6, "head_phrase": 4, "sub_phrase": [], "weight": 0, "element": []}, 
                {"id": 4, "label": "NP_AJT", "text": "P#3@MODㄴ 우리나라 가톨릭에", "begin": 6, "end": 10, "key_begin": 9, "head_phrase": 5, "sub_phrase": [3], "weight": 0, "element": []}, 
                {"id": 5, "label": "VP", "text": "P#4@AJT에 대해", "begin": 6, "end": 11, "key_begin": 11, "head_phrase": 7, "sub_phrase": [4], "weight": 0, "element": []}, 
                {"id": 6, "label": "NP_OBJ", "text": "애정을", "begin": 12, "end": 12, "key_begin": 12, "head_phrase": 7, "sub_phrase": [], "weight": 0, "element": []}, 
                {"id": 7, "label": "VP_MOD", "text": "P#5@VP어 P#6@OBJ을 보여온", "begin": 6, "end": 13, "key_begin": 13, "head_phrase": 8, "sub_phrase": [5, 6], "weight": 0, "element": []}, 
                {"id": 8, "label": "NP_SBJ", "text": "P#7@MODㄴ 프란치스코 교황은", "begin": 6, "end": 15, "key_begin": 14, "head_phrase": 12, "sub_phrase": [7], "weight": 0, "element": []}, 
                {"id": 9, "label": "NP_OBJ", "text": "함박웃음을", "begin": 16, "end": 16, "key_begin": 16, "head_phrase": 10, "sub_phrase": [], "weight": 0, "element": []}, 
                {"id": 10, "label": "VP_MOD", "text": "P#9@OBJ을 지은", "begin": 16, "end": 17, "key_begin": 17, "head_phrase": 11, "sub_phrase": [9], "weight": 0, "element": []}, 
                {"id": 11, "label": "NP_AJT", "text": "P#10@MOD은 것으로", "begin": 16, "end": 18, "key_begin": 18, "head_phrase": 12, "sub_phrase": [10], "weight": 0, "element": []}, 
                {"id": 12, "label": "S", "text": "S#2@S는데요, P#8@SBJ은 P#11@AJT으로 전해졌습니다.", "begin": 0, "end": 19, "key_begin": 19, "head_phrase": -1, "sub_phrase": [2, 8, 11], "weight": 0, "element": []}
            ], 
            "SRL": [
                {"verb": "검", "sense": 1, "word_id": 2, "weight": 0.409914, "argument": [
                    {"type": "ARG1", "word_id": 3, "text": "태권도 도복과 검은 띠", "weight": 0.409914}
                ]}, 
                {"verb": "전달", "sense": 1, "word_id": 5, "weight": 0.400641, "argument": [
                    {"type": "ARG1", "word_id": 3, "text": "태권도 도복과 검은 띠", "weight": 0.545054}, 
                    {"type": "ARGM-ADV", "word_id": 4, "text": "함께", "weight": 1}
                ]}, 
                {"verb": "대", "sense": 1, "word_id": 11, "weight": 0.509892, "argument": [
                    {"type": "ARG2", "word_id": 10, "text": "우리나라 가톨릭", "weight": 0.731402}, 
                    {"type": "ARG1", "word_id": 12, "text": "애정", "weight": 0.288381}
                ]}, 
                {"verb": "보이", "sense": 1, "word_id": 13, "weight": 0.242352, "argument": [
                    {"type": "ARGM-ADV", "word_id": 11, "text": "대해", "weight": 0.267308}, 
                    {"type": "ARG1", "word_id": 12, "text": "애정", "weight": 0.239394}, 
                    {"type": "ARGA", "word_id": 15, "text": "프란치스코 교황", "weight": 0.220355}
                ]}, 
                {"verb": "짓", "sense": 1, "word_id": 17, "weight": 0.381049, "argument": [
                    {"type": "ARG0", "word_id": 15, "text": "프란치스코 교황", "weight": 0.376439}, 
                    {"type": "ARG1", "word_id": 16, "text": "함박웃음", "weight": 0.385659}
                ]}, 
                {"verb": "전하", "sense": 1, "word_id": 19, "weight": 0.361526, "argument": [
                    {"type": "ARG1", "word_id": 18, "text": "것", "weight": 0.361526}
                ]}
            ], 
            "ZA": [
                {"id": 0, "type": "s", "head_wid": 19, "ant_sid": -1, "ant_wid": -1, "ant_is_title": 0, "weight": 1.01}
            ]
        }, 
        {
            "id": 6, 
            "text": "이번 전달식은 인성교육을 중시하는 '태권도 정신'에 초점을 맞췄는데요, 박영길 이탈리아태권도협회 명예회장은 약자에 대한 관심과 따뜻한 인간미를 보여주는 프란치스코 교황이야말로 명예 단증을 받기에 더없이 적합한 인물이라고 소개했습니다.", 
            "morp": [
                {"id": 0, "lemma": "이번", "type": "NNG", "position": 705, "weight": 0.9}, 
                {"id": 1, "lemma": "전달", "type": "NNG", "position": 712, "weight": 0.9}, 
                {"id": 2, "lemma": "식", "type": "XSN", "position": 718, "weight": 0.0146035}, 
                {"id": 3, "lemma": "은", "type": "JX", "position": 721, "weight": 0.100393}, 
                {"id": 4, "lemma": "인성", "type": "NNG", "position": 725, "weight": 0.303884}, 
                {"id": 5, "lemma": "교육", "type": "NNG", "position": 731, "weight": 0.9}, 
                {"id": 6, "lemma": "을", "type": "JKO", "position": 737, "weight": 0.129611}, 
                {"id": 7, "lemma": "중시", "type": "NNG", "position": 741, "weight": 0.9}, 
                {"id": 8, "lemma": "하", "type": "XSV", "position": 747, "weight": 0.0001}, 
                {"id": 9, "lemma": "는", "type": "ETM", "position": 750, "weight": 0.238503}, 
                {"id": 10, "lemma": "'", "type": "SS", "position": 754, "weight": 1}, 
                {"id": 11, "lemma": "태권", "type": "NNG", "position": 755, "weight": 0.171429}, 
                {"id": 12, "lemma": "도", "type": "JX", "position": 761, "weight": 0.0676272}, 
                {"id": 13, "lemma": "정신", "type": "NNG", "position": 765, "weight": 0.324873}, 
                {"id": 14, "lemma": "'", "type": "SS", "position": 771, "weight": 1}, 
                {"id": 15, "lemma": "에", "type": "JKB", "position": 772, "weight": 0.048593}, 
                {"id": 16, "lemma": "초점", "type": "NNG", "position": 776, "weight": 0.9}, 
                {"id": 17, "lemma": "을", "type": "JKO", "position": 782, "weight": 0.129611}, 
                {"id": 18, "lemma": "맞추", "type": "VV", "position": 786, "weight": 0.9}, 
                {"id": 19, "lemma": "었", "type": "EP", "position": 789, "weight": 0.9}, 
                {"id": 20, "lemma": "는데요", "type": "EC", "position": 792, "weight": 0.0215501}, 
                {"id": 21, "lemma": ",", "type": "SP", "position": 801, "weight": 1}, 
                {"id": 22, "lemma": "박영길", "type": "NNP", "position": 803, "weight": 0.2}, 
                {"id": 23, "lemma": "이탈리아태권도", "type": "NNP", "position": 813, "weight": 0.6}, 
                {"id": 24, "lemma": "협회", "type": "NNG", "position": 834, "weight": 0.9}, 
                {"id": 25, "lemma": "명예", "type": "NNG", "position": 841, "weight": 0.9}, 
                {"id": 26, "lemma": "회장", "type": "NNG", "position": 847, "weight": 0.184788}, 
                {"id": 27, "lemma": "은", "type": "JX", "position": 853, "weight": 0.0449928}, 
                {"id": 28, "lemma": "약자", "type": "NNG", "position": 857, "weight": 0.9}, 
                {"id": 29, "lemma": "에", "type": "JKB", "position": 863, "weight": 0.153364}, 
                {"id": 30, "lemma": "대", "type": "NNG", "position": 867, "weight": 0.0312871}, 
                {"id": 31, "lemma": "하", "type": "XSV", "position": 870, "weight": 0.0001}, 
                {"id": 32, "lemma": "ㄴ", "type": "ETM", "position": 870, "weight": 0.392321}, 
                {"id": 33, "lemma": "관심", "type": "NNG", "position": 874, "weight": 0.9}, 
                {"id": 34, "lemma": "과", "type": "JC", "position": 880, "weight": 0.017569}, 
                {"id": 35, "lemma": "따뜻하", "type": "VA", "position": 884, "weight": 0.9}, 
                {"id": 36, "lemma": "ㄴ", "type": "ETM", "position": 890, "weight": 0.430446}, 
                {"id": 37, "lemma": "인간", "type": "NNG", "position": 894, "weight": 0.9}, 
                {"id": 38, "lemma": "미", "type": "NNG", "position": 900, "weight": 0.0285291}, 
                {"id": 39, "lemma": "를", "type": "JKO", "position": 903, "weight": 0.137686}, 
                {"id": 40, "lemma": "보이", "type": "VV", "position": 907, "weight": 0.776105}, 
                {"id": 41, "lemma": "어", "type": "EC", "position": 910, "weight": 0.41831}, 
                {"id": 42, "lemma": "주", "type": "VX", "position": 913, "weight": 0.161283}, 
                {"id": 43, "lemma": "는", "type": "ETM", "position": 916, "weight": 0.183966}, 
                {"id": 44, "lemma": "프란치스코", "type": "NNP", "position": 920, "weight": 0.75}, 
                {"id": 45, "lemma": "교황", "type": "NNG", "position": 936, "weight": 0.9}, 
                {"id": 46, "lemma": "이야말로", "type": "JX", "position": 942, "weight": 0.067541}, 
                {"id": 47, "lemma": "명예", "type": "NNG", "position": 955, "weight": 0.9}, 
                {"id": 48, "lemma": "단증", "type": "NNG", "position": 962, "weight": 0}, 
                {"id": 49, "lemma": "을", "type": "JKO", "position": 968, "weight": 0.129611}, 
                {"id": 50, "lemma": "받", "type": "VV", "position": 972, "weight": 0.765648}, 
                {"id": 51, "lemma": "기", "type": "ETN", "position": 975, "weight": 0.0380514}, 
                {"id": 52, "lemma": "에", "type": "JKB", "position": 978, "weight": 0.131408}, 
                {"id": 53, "lemma": "더없이", "type": "MAG", "position": 982, "weight": 0.9}, 
                {"id": 54, "lemma": "적합", "type": "NNG", "position": 992, "weight": 0.55}, 
                {"id": 55, "lemma": "하", "type": "XSA", "position": 998, "weight": 0.0001}, 
                {"id": 56, "lemma": "ㄴ", "type": "ETM", "position": 998, "weight": 0.488779}, 
                {"id": 57, "lemma": "인물", "type": "NNG", "position": 1002, "weight": 0.65867}, 
                {"id": 58, "lemma": "이", "type": "VCP", "position": 1008, "weight": 0.0177525}, 
                {"id": 59, "lemma": "라고", "type": "EC", "position": 1011, "weight": 0.204147}, 
                {"id": 60, "lemma": "소개", "type": "NNG", "position": 1018, "weight": 0.9}, 
                {"id": 61, "lemma": "하", "type": "XSV", "position": 1024, "weight": 0.0001}, 
                {"id": 62, "lemma": "었", "type": "EP", "position": 1024, "weight": 0.9}, 
                {"id": 63, "lemma": "습니다", "type": "EF", "position": 1027, "weight": 0.660908}, 
                {"id": 64, "lemma": ".", "type": "SF", "position": 1036, "weight": 1}
            ], 
            "word": [
                {"id": 0, "text": "이번", "type": "", "begin": 0, "end": 0}, 
                {"id": 1, "text": "전달식은", "type": "", "begin": 1, "end": 3}, 
                {"id": 2, "text": "인성교육을", "type": "", "begin": 4, "end": 6}, 
                {"id": 3, "text": "중시하는", "type": "", "begin": 7, "end": 9}, 
                {"id": 4, "text": "'태권도", "type": "", "begin": 10, "end": 12}, 
                {"id": 5, "text": "정신'에", "type": "", "begin": 13, "end": 15}, 
                {"id": 6, "text": "초점을", "type": "", "begin": 16, "end": 17}, 
                {"id": 7, "text": "맞췄는데요,", "type": "", "begin": 18, "end": 21}, 
                {"id": 8, "text": "박영길", "type": "", "begin": 22, "end": 22}, 
                {"id": 9, "text": "이탈리아태권도협회", "type": "", "begin": 23, "end": 24}, 
                {"id": 10, "text": "명예회장은", "type": "", "begin": 25, "end": 27}, 
                {"id": 11, "text": "약자에", "type": "", "begin": 28, "end": 29}, 
                {"id": 12, "text": "대한", "type": "", "begin": 30, "end": 32}, 
                {"id": 13, "text": "관심과", "type": "", "begin": 33, "end": 34}, 
                {"id": 14, "text": "따뜻한", "type": "", "begin": 35, "end": 36}, 
                {"id": 15, "text": "인간미를", "type": "", "begin": 37, "end": 39}, 
                {"id": 16, "text": "보여주는", "type": "", "begin": 40, "end": 43}, 
                {"id": 17, "text": "프란치스코", "type": "", "begin": 44, "end": 44}, 
                {"id": 18, "text": "교황이야말로", "type": "", "begin": 45, "end": 46}, 
                {"id": 19, "text": "명예", "type": "", "begin": 47, "end": 47}, 
                {"id": 20, "text": "단증을", "type": "", "begin": 48, "end": 49}, 
                {"id": 21, "text": "받기에", "type": "", "begin": 50, "end": 52}, 
                {"id": 22, "text": "더없이", "type": "", "begin": 53, "end": 53}, 
                {"id": 23, "text": "적합한", "type": "", "begin": 54, "end": 56}, 
                {"id": 24, "text": "인물이라고", "type": "", "begin": 57, "end": 59}, 
                {"id": 25, "text": "소개했습니다.", "type": "", "begin": 60, "end": 64}
            ], 
            "NE": [
                {"id": 0, "text": "태권도", "type": "CV_SPORTS", "begin": 11, "end": 12, "weight": 0.752372, "common_noun": 0}, 
                {"id": 1, "text": "박영길", "type": "PS_NAME", "begin": 22, "end": 22, "weight": 0.656854, "common_noun": 0}, 
                {"id": 2, "text": "이탈리아태권도협회", "type": "OGG_SPORTS", "begin": 23, "end": 24, "weight": 0.653286, "common_noun": 0}, 
                {"id": 3, "text": "명예회장", "type": "CV_POSITION", "begin": 25, "end": 26, "weight": 0.806353, "common_noun": 0}, 
                {"id": 4, "text": "프란치스코", "type": "PS_NAME", "begin": 44, "end": 44, "weight": 0.294362, "common_noun": 0}, 
                {"id": 5, "text": "교황", "type": "CV_POSITION", "begin": 45, "end": 45, "weight": 0.688591, "common_noun": 0}
            ], 
            "dependency": [
                {"id": 0, "text": "이번", "head": 1, "label": "NP", "mod": [], "weight": 0.646987}, 
                {"id": 1, "text": "전달식은", "head": 7, "label": "NP_SBJ", "mod": [0], "weight": 0.526321}, 
                {"id": 2, "text": "인성교육을", "head": 3, "label": "NP_OBJ", "mod": [], "weight": 0.708133}, 
                {"id": 3, "text": "중시하는", "head": 5, "label": "VP_MOD", "mod": [2], "weight": 0.667429}, 
                {"id": 4, "text": "'태권도", "head": 5, "label": "NP", "mod": [], "weight": 0.417034}, 
                {"id": 5, "text": "정신'에", "head": 7, "label": "NP_AJT", "mod": [3, 4], "weight": 0.52338}, 
                {"id": 6, "text": "초점을", "head": 7, "label": "NP_OBJ", "mod": [], "weight": 0.737322}, 
                {"id": 7, "text": "맞췄는데요,", "head": 21, "label": "VP", "mod": [1, 5, 6], "weight": 0.234043}, 
                {"id": 8, "text": "박영길", "head": 10, "label": "NP", "mod": [], "weight": 0.652312}, 
                {"id": 9, "text": "이탈리아태권도협회", "head": 10, "label": "NP", "mod": [], "weight": 0.776629}, 
                {"id": 10, "text": "명예회장은", "head": 21, "label": "NP_SBJ", "mod": [8, 9], "weight": 0.343778}, 
                {"id": 11, "text": "약자에", "head": 12, "label": "NP_AJT", "mod": [], "weight": 0.601505}, 
                {"id": 12, "text": "대한", "head": 13, "label": "VP_MOD", "mod": [11], "weight": 0.579064}, 
                {"id": 13, "text": "관심과", "head": 15, "label": "NP_CNJ", "mod": [12], "weight": 0.498518}, 
                {"id": 14, "text": "따뜻한", "head": 15, "label": "VP_MOD", "mod": [], "weight": 0.631552}, 
                {"id": 15, "text": "인간미를", "head": 16, "label": "NP_OBJ", "mod": [13, 14], "weight": 0.685024}, 
                {"id": 16, "text": "보여주는", "head": 18, "label": "VP_MOD", "mod": [15], "weight": 0.488116}, 
                {"id": 17, "text": "프란치스코", "head": 18, "label": "NP", "mod": [], "weight": 0.808654}, 
                {"id": 18, "text": "교황이야말로", "head": 21, "label": "NP_SBJ", "mod": [16, 17], "weight": 0.751762}, 
                {"id": 19, "text": "명예", "head": 20, "label": "NP", "mod": [], "weight": 0.771011}, 
                {"id": 20, "text": "단증을", "head": 21, "label": "NP_OBJ", "mod": [19], "weight": 0.758498}, 
                {"id": 21, "text": "받기에", "head": 23, "label": "VP_AJT", "mod": [7, 10, 18, 20], "weight": 0.638005}, 
                {"id": 22, "text": "더없이", "head": 23, "label": "AP", "mod": [], "weight": 0.863164}, 
                {"id": 23, "text": "적합한", "head": 24, "label": "VP_MOD", "mod": [21, 22], "weight": 0.764642}, 
                {"id": 24, "text": "인물이라고", "head": 25, "label": "VNP_CMP", "mod": [23], "weight": 0.568385}, 
                {"id": 25, "text": "소개했습니다.", "head": -1, "label": "VP", "mod": [24], "weight": 2.88947e-06}
            ], 
            "phrase_dependency": [
                {"id": 0, "label": "NP_SBJ", "text": "이번 전달식은", "begin": 0, "end": 1, "key_begin": 0, "head_phrase": 5, "sub_phrase": [], "weight": 0, "element": []}, 
                {"id": 1, "label": "NP_OBJ", "text": "인성교육을", "begin": 2, "end": 2, "key_begin": 2, "head_phrase": 2, "sub_phrase": [], "weight": 0, "element": []}, 
                {"id": 2, "label": "VP_MOD", "text": "P#1@OBJ을 중시하는", "begin": 2, "end": 3, "key_begin": 3, "head_phrase": 3, "sub_phrase": [1], "weight": 0, "element": []}, 
                {"id": 3, "label": "NP_AJT", "text": "P#2@MOD는 '태권도 정신'에", "begin": 2, "end": 5, "key_begin": 4, "head_phrase": 5, "sub_phrase": [2], "weight": 0, "element": []}, 
                {"id": 4, "label": "NP_OBJ", "text": "초점을", "begin": 6, "end": 6, "key_begin": 6, "head_phrase": 5, "sub_phrase": [], "weight": 0, "element": []}, 
                {"id": 5, "label": "S", "text": "P#0@SBJ은 P#3@AJT에 P#4@OBJ을 맞췄는데요,", "begin": 0, "end": 7, "key_begin": 7, "head_phrase": 13, "sub_phrase": [0, 3, 4], "weight": 0, "element": []}, 
                {"id": 6, "label": "NP_SBJ", "text": "박영길 이탈리아태권도협회 명예회장은", "begin": 8, "end": 10, "key_begin": 8, "head_phrase": 13, "sub_phrase": [], "weight": 0, "element": []}, 
                {"id": 7, "label": "NP_AJT", "text": "약자에", "begin": 11, "end": 11, "key_begin": 11, "head_phrase": 8, "sub_phrase": [], "weight": 0, "element": []}, 
                {"id": 8, "label": "VP_MOD", "text": "P#7@AJT에 대한", "begin": 11, "end": 12, "key_begin": 12, "head_phrase": 9, "sub_phrase": [7], "weight": 0, "element": []}, 
                {"id": 9, "label": "NP_OBJ", "text": "P#8@MODㄴ 관심과 따뜻한 인간미를", "begin": 11, "end": 15, "key_begin": 13, "head_phrase": 10, "sub_phrase": [8], "weight": 0, "element": [
                    {"text": "약자에 대한 관심", "label": "NP_OBJ", "begin": 28, "end": 33, "ne_type": ""}, 
                    {"text": "따뜻한 인간미", "label": "NP_OBJ", "begin": 35, "end": 38, "ne_type": ""}
                ]}, 
                {"id": 10, "label": "VP_MOD", "text": "P#9@OBJ를 보여주는", "begin": 11, "end": 16, "key_begin": 16, "head_phrase": 11, "sub_phrase": [9], "weight": 0, "element": []}, 
                {"id": 11, "label": "NP_SBJ", "text": "P#10@MOD는 프란치스코 교황이야말로", "begin": 11, "end": 18, "key_begin": 17, "head_phrase": 13, "sub_phrase": [10], "weight": 0, "element": []}, 
                {"id": 12, "label": "NP_OBJ", "text": "명예 단증을", "begin": 19, "end": 20, "key_begin": 19, "head_phrase": 13, "sub_phrase": [], "weight": 0, "element": []}, 
                {"id": 13, "label": "S_AJT", "text": "S#5@S는데요, P#6@SBJ은 P#11@SBJ이야말로 P#12@OBJ을 받기에", "begin": 0, "end": 21, "key_begin": 21, "head_phrase": 15, "sub_phrase": [5, 6, 11, 12], "weight": 0, "element": []}, 
                {"id": 14, "label": "AP", "text": "더없이", "begin": 22, "end": 22, "key_begin": 22, "head_phrase": 15, "sub_phrase": [], "weight": 0, "element": []}, 
                {"id": 15, "label": "S_MOD", "text": "S#13@AJT에 P#14@AP더없이 적합한", "begin": 0, "end": 23, "key_begin": 23, "head_phrase": 16, "sub_phrase": [13, 14], "weight": 0, "element": []}, 
                {"id": 16, "label": "S_CMP", "text": "S#15@MODㄴ 인물이라고", "begin": 0, "end": 24, "key_begin": 24, "head_phrase": 17, "sub_phrase": [15], "weight": 0, "element": []}, 
                {"id": 17, "label": "S", "text": "S#16@CMP라고 소개했습니다.", "begin": 0, "end": 25, "key_begin": 25, "head_phrase": -1, "sub_phrase": [16], "weight": 0, "element": []}
            ], 
            "SRL": [
                {"verb": "중시", "sense": 1, "word_id": 3, "weight": 0.28655, "argument": [
                    {"type": "ARG0", "word_id": 1, "text": "이번 전달식", "weight": 0.250924}, 
                    {"type": "ARG1", "word_id": 2, "text": "인성교육", "weight": 0.438786}, 
                    {"type": "ARG0", "word_id": 5, "text": "'태권도 정신'", "weight": 0.16994}
                ]}, 
                {"verb": "맞추", "sense": 1, "word_id": 7, "weight": 0.382442, "argument": [
                    {"type": "ARG0", "word_id": 1, "text": "이번 전달식", "weight": 0.28624}, 
                    {"type": "ARG2", "word_id": 5, "text": "'태권도 정신'", "weight": 0.482611}, 
                    {"type": "ARG1", "word_id": 6, "text": "초점", "weight": 0.378473}
                ]}, 
                {"verb": "대", "sense": 1, "word_id": 12, "weight": 0.637148, "argument": [
                    {"type": "ARG2", "word_id": 11, "text": "약자", "weight": 0.604939}, 
                    {"type": "ARG1", "word_id": 13, "text": "관심", "weight": 0.669356}
                ]}, 
                {"verb": "따뜻하", "sense": 1, "word_id": 14, "weight": 0.37933, "argument": [
                    {"type": "ARG1", "word_id": 15, "text": "관심과 따뜻한 인간미", "weight": 0.37933}
                ]}, 
                {"verb": "보이", "sense": 1, "word_id": 16, "weight": 0.256788, "argument": [
                    {"type": "ARG1", "word_id": 15, "text": "관심과 따뜻한 인간미", "weight": 0.308836}, 
                    {"type": "ARGA", "word_id": 18, "text": "프란치스코 교황", "weight": 0.20474}
                ]}, 
                {"verb": "받", "sense": 1, "word_id": 21, "weight": 0.491445, "argument": [
                    {"type": "ARG1", "word_id": 20, "text": "명예 단증", "weight": 0.491445}
                ]}, 
                {"verb": "적합", "sense": 1, "word_id": 23, "weight": 0.246907, "argument": [
                    {"type": "ARG2", "word_id": 21, "text": "받기", "weight": 0.21598}, 
                    {"type": "ARGM-EXT", "word_id": 22, "text": "더없이", "weight": 0.262798}, 
                    {"type": "ARG1", "word_id": 24, "text": "인물이라고", "weight": 0.261944}
                ]}, 
                {"verb": "소개", "sense": 1, "word_id": 25, "weight": 0.151844, "argument": [
                    {"type": "ARG1", "word_id": 24, "text": "인물이라고", "weight": 0.151844}
                ]}
            ], 
            "ZA": [
                {"id": 0, "type": "s", "head_wid": 23, "ant_sid": 6, "ant_wid": 18, "ant_is_title": 0, "weight": 1.01}, 
                {"id": 1, "type": "s", "head_wid": 24, "ant_sid": 6, "ant_wid": 18, "ant_is_title": 0, "weight": 1.01}
            ]
        }, 
        {
            "id": 7, 
            "text": "누리꾼들은 '나무 합판조차 파괴 반대하실 것 같지만 그래도 축하합니다!', '10단이 어울릴 만큼 강인해 보인다.", 
            "morp": [
                {"id": 0, "lemma": "누리꾼", "type": "NNG", "position": 1037, "weight": 0}, 
                {"id": 1, "lemma": "들", "type": "XSN", "position": 1046, "weight": 0.0299841}, 
                {"id": 2, "lemma": "은", "type": "JX", "position": 1049, "weight": 0.100393}, 
                {"id": 3, "lemma": "'", "type": "SS", "position": 1053, "weight": 1}, 
                {"id": 4, "lemma": "나무", "type": "NNG", "position": 1054, "weight": 0.199976}, 
                {"id": 5, "lemma": "합판", "type": "NNG", "position": 1061, "weight": 0.9}, 
                {"id": 6, "lemma": "조차", "type": "JX", "position": 1067, "weight": 0.0684722}, 
                {"id": 7, "lemma": "파괴", "type": "NNG", "position": 1074, "weight": 0.9}, 
                {"id": 8, "lemma": "반대", "type": "NNG", "position": 1081, "weight": 0.9}, 
                {"id": 9, "lemma": "하", "type": "XSV", "position": 1087, "weight": 0.0001}, 
                {"id": 10, "lemma": "시", "type": "EP", "position": 1090, "weight": 0.0676193}, 
                {"id": 11, "lemma": "ㄹ", "type": "ETM", "position": 1090, "weight": 0.101888}, 
                {"id": 12, "lemma": "것", "type": "NNB", "position": 1094, "weight": 0.228788}, 
                {"id": 13, "lemma": "같", "type": "VA", "position": 1098, "weight": 0.101272}, 
                {"id": 14, "lemma": "지만", "type": "EC", "position": 1101, "weight": 0.315566}, 
                {"id": 15, "lemma": "그리", "type": "MAG", "position": 1108, "weight": 0.0106026}, 
                {"id": 16, "lemma": "하", "type": "XSV", "position": 1114, "weight": 0.0001}, 
                {"id": 17, "lemma": "어도", "type": "EC", "position": 1114, "weight": 0.372034}, 
                {"id": 18, "lemma": "축하", "type": "NNG", "position": 1118, "weight": 0.218826}, 
                {"id": 19, "lemma": "하", "type": "XSV", "position": 1124, "weight": 0.0001}, 
                {"id": 20, "lemma": "ㅂ니다", "type": "EF", "position": 1124, "weight": 0.0449374}, 
                {"id": 21, "lemma": "!", "type": "SF", "position": 1133, "weight": 1}, 
                {"id": 22, "lemma": "'", "type": "SS", "position": 1134, "weight": 1}, 
                {"id": 23, "lemma": ",", "type": "SP", "position": 1135, "weight": 1}, 
                {"id": 24, "lemma": "'", "type": "SS", "position": 1137, "weight": 1}, 
                {"id": 25, "lemma": "10", "type": "SN", "position": 1138, "weight": 1}, 
                {"id": 26, "lemma": "단", "type": "NNB", "position": 1140, "weight": 0.00866069}, 
                {"id": 27, "lemma": "이", "type": "JKS", "position": 1143, "weight": 0.0376169}, 
                {"id": 28, "lemma": "어울리", "type": "VV", "position": 1147, "weight": 0.9}, 
                {"id": 29, "lemma": "ㄹ", "type": "ETM", "position": 1153, "weight": 0.300746}, 
                {"id": 30, "lemma": "만큼", "type": "NNB", "position": 1157, "weight": 0.156941}, 
                {"id": 31, "lemma": "강인", "type": "NNG", "position": 1164, "weight": 0.0368724}, 
                {"id": 32, "lemma": "하", "type": "XSA", "position": 1170, "weight": 0.0001}, 
                {"id": 33, "lemma": "어", "type": "EC", "position": 1170, "weight": 0.354073}, 
                {"id": 34, "lemma": "보이", "type": "VV", "position": 1174, "weight": 0.225864}, 
                {"id": 35, "lemma": "ㄴ다", "type": "EF", "position": 1177, "weight": 0.0793196}, 
                {"id": 36, "lemma": ".", "type": "SF", "position": 1183, "weight": 1}
            ], 
            "word": [
                {"id": 0, "text": "누리꾼들은", "type": "", "begin": 0, "end": 2}, 
                {"id": 1, "text": "'나무", "type": "", "begin": 3, "end": 4}, 
                {"id": 2, "text": "합판조차", "type": "", "begin": 5, "end": 6}, 
                {"id": 3, "text": "파괴", "type": "", "begin": 7, "end": 7}, 
                {"id": 4, "text": "반대하실", "type": "", "begin": 8, "end": 11}, 
                {"id": 5, "text": "것", "type": "", "begin": 12, "end": 12}, 
                {"id": 6, "text": "같지만", "type": "", "begin": 13, "end": 14}, 
                {"id": 7, "text": "그래도", "type": "", "begin": 15, "end": 17}, 
                {"id": 8, "text": "축하합니다!',", "type": "", "begin": 18, "end": 23}, 
                {"id": 9, "text": "'10단이", "type": "", "begin": 24, "end": 27}, 
                {"id": 10, "text": "어울릴", "type": "", "begin": 28, "end": 29}, 
                {"id": 11, "text": "만큼", "type": "", "begin": 30, "end": 30}, 
                {"id": 12, "text": "강인해", "type": "", "begin": 31, "end": 33}, 
                {"id": 13, "text": "보인다.", "type": "", "begin": 34, "end": 36}
            ], 
            "NE": [
                {"id": 0, "text": "누리꾼", "type": "CV_POSITION", "begin": 0, "end": 0, "weight": 0.378242, "common_noun": 0}, 
                {"id": 1, "text": "10단", "type": "QT_ORDER", "begin": 25, "end": 26, "weight": 0.625216, "common_noun": 0}
            ], 
            "dependency": [
                {"id": 0, "text": "누리꾼들은", "head": 6, "label": "NP_SBJ", "mod": [], "weight": 0.265667}, 
                {"id": 1, "text": "'나무", "head": 2, "label": "NP", "mod": [], "weight": 0.66216}, 
                {"id": 2, "text": "합판조차", "head": 4, "label": "NP_SBJ", "mod": [1], "weight": 0.521868}, 
                {"id": 3, "text": "파괴", "head": 4, "label": "NP", "mod": [], "weight": 0.431126}, 
                {"id": 4, "text": "반대하실", "head": 5, "label": "VP_MOD", "mod": [2, 3], "weight": 0.729231}, 
                {"id": 5, "text": "것", "head": 6, "label": "NP", "mod": [4], "weight": 0.713974}, 
                {"id": 6, "text": "같지만", "head": 7, "label": "VP", "mod": [0, 5], "weight": 0.477363}, 
                {"id": 7, "text": "그래도", "head": 8, "label": "VP", "mod": [6], "weight": 0.651211}, 
                {"id": 8, "text": "축하합니다!',", "head": 12, "label": "VP", "mod": [7], "weight": 0.329571}, 
                {"id": 9, "text": "'10단이", "head": 10, "label": "NP_SBJ", "mod": [], "weight": 0.722018}, 
                {"id": 10, "text": "어울릴", "head": 11, "label": "VP_MOD", "mod": [9], "weight": 0.863695}, 
                {"id": 11, "text": "만큼", "head": 12, "label": "NP_AJT", "mod": [10], "weight": 0.878805}, 
                {"id": 12, "text": "강인해", "head": 13, "label": "VP", "mod": [8, 11], "weight": 0.736098}, 
                {"id": 13, "text": "보인다.", "head": -1, "label": "VP", "mod": [12], "weight": 0.000743266}
            ], 
            "phrase_dependency": [
                {"id": 0, "label": "NP_SBJ", "text": "누리꾼들은", "begin": 0, "end": 0, "key_begin": 0, "head_phrase": 3, "sub_phrase": [], "weight": 0, "element": []}, 
                {"id": 1, "label": "NP_SBJ", "text": "'나무 합판조차", "begin": 1, "end": 2, "key_begin": 1, "head_phrase": 2, "sub_phrase": [], "weight": 0, "element": []}, 
                {"id": 2, "label": "S_MOD", "text": "P#1@SBJ조차 파괴 반대하실", "begin": 1, "end": 4, "key_begin": 3, "head_phrase": 3, "sub_phrase": [1], "weight": 0, "element": []}, 
                {"id": 3, "label": "S", "text": "P#0@SBJ은 S#2@MODㄹ 것 같지만 그래도 축하합니다!',", "begin": 0, "end": 8, "key_begin": 5, "head_phrase": 7, "sub_phrase": [0, 2], "weight": 0, "element": []}, 
                {"id": 4, "label": "NP_SBJ", "text": "'10단이", "begin": 9, "end": 9, "key_begin": 9, "head_phrase": 5, "sub_phrase": [], "weight": 0, "element": []}, 
                {"id": 5, "label": "S_MOD", "text": "P#4@SBJ이 어울릴", "begin": 9, "end": 10, "key_begin": 10, "head_phrase": 6, "sub_phrase": [4], "weight": 0, "element": []}, 
                {"id": 6, "label": "NP_AJT", "text": "S#5@MODㄹ 만큼", "begin": 9, "end": 11, "key_begin": 11, "head_phrase": 7, "sub_phrase": [5], "weight": 0, "element": []}, 
                {"id": 7, "label": "S", "text": "S#3@S', P#6@AJT만큼 강인해 보인다.", "begin": 0, "end": 13, "key_begin": 12, "head_phrase": -1, "sub_phrase": [3, 6], "weight": 0, "element": []}
            ], 
            "SRL": [
                {"verb": "반대", "sense": 1, "word_id": 4, "weight": 0.373342, "argument": [
                    {"type": "ARG0", "word_id": 2, "text": "'나무 합판", "weight": 0.286131}, 
                    {"type": "AUX", "word_id": 6, "text": "같지만", "weight": 0.460552}
                ]}, 
                {"verb": "같", "sense": 1, "word_id": 6, "weight": 0, "argument": []}, 
                {"verb": "그리", "sense": 1, "word_id": 7, "weight": 0.0796041, "argument": [
                    {"type": "ARGM-INS", "word_id": 6, "text": "같지만", "weight": 1}
                ]}, 
                {"verb": "축하", "sense": 1, "word_id": 8, "weight": 0.136623, "argument": [
                    {"type": "ARGM-DIS", "word_id": 6, "text": "같지만", "weight": 0.189658}, 
                    {"type": "ARGM-DIS", "word_id": 7, "text": "그래도", "weight": 0.0835872}
                ]}, 
                {"verb": "어울리", "sense": 1, "word_id": 10, "weight": 0.292575, "argument": [
                    {"type": "ARG1", "word_id": 9, "text": "'10단", "weight": 0.292575}
                ]}, 
                {"verb": "강인", "sense": 1, "word_id": 12, "weight": 0.149664, "argument": [
                    {"type": "ARGM-EXT", "word_id": 11, "text": "만큼", "weight": 0.149664}
                ]}, 
                {"verb": "보이", "sense": 1, "word_id": 13, "weight": 0.115416, "argument": [
                    {"type": "ARGM-CAU", "word_id": 12, "text": "강인해", "weight": 0.115416}
                ]}
            ], 
            "ZA": [
                {"id": 0, "type": "s", "head_wid": 4, "ant_sid": 6, "ant_wid": 18, "ant_is_title": 0, "weight": 1.01}, 
                {"id": 1, "type": "s", "head_wid": 10, "ant_sid": 6, "ant_wid": 18, "ant_is_title": 0, "weight": 1.01}, 
                {"id": 2, "type": "s", "head_wid": 12, "ant_sid": 6, "ant_wid": 18, "ant_is_title": 0, "weight": 1.01}
            ]
        }, 
        {
            "id": 8, 
            "text": " 내유외강형 고수!'등의 반응을 보였습니다.", 
            "morp": [
                {"id": 0, "lemma": "내유외강형", "type": "NNG", "position": 1185, "weight": 0}, 
                {"id": 1, "lemma": "고수", "type": "NNG", "position": 1201, "weight": 0.183591}, 
                {"id": 2, "lemma": "!", "type": "SF", "position": 1207, "weight": 1}, 
                {"id": 3, "lemma": "'", "type": "SS", "position": 1208, "weight": 1}, 
                {"id": 4, "lemma": "등", "type": "NNB", "position": 1209, "weight": 0.0121753}, 
                {"id": 5, "lemma": "의", "type": "JKG", "position": 1212, "weight": 0.0520933}, 
                {"id": 6, "lemma": "반응", "type": "NNG", "position": 1216, "weight": 0.9}, 
                {"id": 7, "lemma": "을", "type": "JKO", "position": 1222, "weight": 0.129611}, 
                {"id": 8, "lemma": "보이", "type": "VV", "position": 1226, "weight": 0.776105}, 
                {"id": 9, "lemma": "었", "type": "EP", "position": 1229, "weight": 0.9}, 
                {"id": 10, "lemma": "습니다", "type": "EF", "position": 1232, "weight": 0.660908}, 
                {"id": 11, "lemma": ".", "type": "SF", "position": 1241, "weight": 1}
            ], 
            "word": [
                {"id": 0, "text": "내유외강형", "type": "", "begin": 0, "end": 0}, 
                {"id": 1, "text": "고수!'등의", "type": "", "begin": 1, "end": 5}, 
                {"id": 2, "text": "반응을", "type": "", "begin": 6, "end": 7}, 
                {"id": 3, "text": "보였습니다.", "type": "", "begin": 8, "end": 11}
            ], 
            "NE": [
                {"id": 0, "text": "고수", "type": "CV_POSITION", "begin": 1, "end": 1, "weight": 0.338233, "common_noun": 0}
            ], 
            "dependency": [
                {"id": 0, "text": "내유외강형", "head": 1, "label": "NP", "mod": [], "weight": 0.699522}, 
                {"id": 1, "text": "고수!'등의", "head": 2, "label": "NP_MOD", "mod": [0], "weight": 0.664109}, 
                {"id": 2, "text": "반응을", "head": 3, "label": "NP_OBJ", "mod": [1], "weight": 0.741141}, 
                {"id": 3, "text": "보였습니다.", "head": -1, "label": "VP", "mod": [2], "weight": 0.286704}
            ], 
            "phrase_dependency": [
                {"id": 0, "label": "NP_OBJ", "text": "내유외강형 고수!'등의 반응을", "begin": 0, "end": 2, "key_begin": 0, "head_phrase": 1, "sub_phrase": [], "weight": 0, "element": []}, 
                {"id": 1, "label": "VP", "text": "P#0@OBJ을 보였습니다.", "begin": 0, "end": 3, "key_begin": 3, "head_phrase": -1, "sub_phrase": [0], "weight": 0, "element": []}
            ], 
            "SRL": [
                {"verb": "보이", "sense": 1, "word_id": 3, "weight": 0.382158, "argument": [
                    {"type": "ARG1", "word_id": 2, "text": "내유외강형 고수!'등의 반응", "weight": 0.382158}
                ]}
            ], 
            "ZA": []
        }
    ], 
    "entity": [
        {"id": 0, "type": "PS_NAME", "number": "singular", "gender": "", "person": "", "animacy": "", "loc": "", "mention": [
            {"id": 1, "sent_id": 0, "start_eid": 1, "end_eid": 2, "ne_id": 2, "text": "프란치스코 교황", "start_eid_short": 1, "end_eid_short": 2, "text_short": "프란치스코 교황", "weight": 0.104}, 
            {"id": 2, "sent_id": 0, "start_eid": 1, "end_eid": 1, "ne_id": 1, "text": "프란치스코", "start_eid_short": 1, "end_eid_short": 1, "text_short": "프란치스코", "weight": 0.0989999}, 
            {"id": 11, "sent_id": 2, "start_eid": 6, "end_eid": 8, "ne_id": 1, "text": "이 명예단증의 주인공", "start_eid_short": 6, "end_eid_short": 8, "text_short": "이 명예단증의 주인공", "weight": 0.104}, 
            {"id": 13, "sent_id": 2, "start_eid": 10, "end_eid": 10, "ne_id": 2, "text": "프란치스코", "start_eid_short": 10, "end_eid_short": 10, "text_short": "프란치스코", "weight": 0.105}, 
            {"id": 22, "sent_id": 4, "start_eid": 2, "end_eid": 3, "ne_id": 4, "text": "프란치스코 교황", "start_eid_short": 2, "end_eid_short": 3, "text_short": "프란치스코 교황", "weight": 0.11}, 
            {"id": 23, "sent_id": 4, "start_eid": 2, "end_eid": 2, "ne_id": 3, "text": "프란치스코", "start_eid_short": 2, "end_eid_short": 2, "text_short": "프란치스코", "weight": 0.105}, 
            {"id": 37, "sent_id": 5, "start_eid": 14, "end_eid": 14, "ne_id": 3, "text": "프란치스코", "start_eid_short": 14, "end_eid_short": 14, "text_short": "프란치스코", "weight": 0.105}, 
            {"id": 55, "sent_id": 6, "start_eid": 17, "end_eid": 17, "ne_id": 4, "text": "프란치스코", "start_eid_short": 17, "end_eid_short": 17, "text_short": "프란치스코", "weight": 0.105}
        ]}, 
        {"id": 1, "type": "QT_ORDER", "number": "singular", "gender": "", "person": "", "animacy": "", "loc": "", "mention": [
            {"id": 10, "sent_id": 2, "start_eid": 5, "end_eid": 5, "ne_id": 0, "text": "10단이ㄴ데", "start_eid_short": 5, "end_eid_short": 5, "text_short": "10단이ㄴ데", "weight": 0.003}, 
            {"id": 19, "sent_id": 3, "start_eid": 6, "end_eid": 6, "ne_id": 3, "text": "10단'이ㅂ니다.", "start_eid_short": 6, "end_eid_short": 6, "text_short": "10단'이ㅂ니다.", "weight": 0.01}, 
            {"id": 3, "sent_id": 0, "start_eid": 3, "end_eid": 4, "ne_id": 4, "text": "'태권도 10단'…명예", "start_eid_short": 4, "end_eid_short": 4, "text_short": "10단'…명예", "weight": 0.006}
        ]}, 
        {"id": 2, "type": "", "number": "singular", "gender": "", "person": "", "animacy": "", "loc": "", "mention": [
            {"id": 5, "sent_id": 0, "start_eid": 5, "end_eid": 5, "ne_id": -1, "text": "단증", "start_eid_short": 5, "end_eid_short": 5, "text_short": "단증", "weight": 0.002}, 
            {"id": 8, "sent_id": 1, "start_eid": 3, "end_eid": 4, "ne_id": -1, "text": "태권도 단증", "start_eid_short": 3, "end_eid_short": 4, "text_short": "태권도 단증", "weight": 0.0035}, 
            {"id": 56, "sent_id": 6, "start_eid": 19, "end_eid": 20, "ne_id": -1, "text": "명예 단증", "start_eid_short": 19, "end_eid_short": 20, "text_short": "명예 단증", "weight": 0.0035}
        ]}, 
        {"id": 3, "type": "", "number": "singular", "gender": "", "person": "", "animacy": "", "loc": "", "mention": [
            {"id": 12, "sent_id": 2, "start_eid": 6, "end_eid": 7, "ne_id": -1, "text": "이 명예단증", "start_eid_short": 6, "end_eid_short": 7, "text_short": "이 명예단증", "weight": 0.006}, 
            {"id": 7, "sent_id": 1, "start_eid": 1, "end_eid": 5, "ne_id": -1, "text": "조금 특별한 태권도 단증 수여식", "start_eid_short": 3, "end_eid_short": 5, "text_short": "태권도 단증 수여식", "weight": 0.002}
        ]}, 
        {"id": 4, "type": "", "number": "singular", "gender": "", "person": "", "animacy": "", "loc": "", "mention": [
            {"id": 25, "sent_id": 4, "start_eid": 4, "end_eid": 5, "ne_id": -1, "text": "태권도 명예", "start_eid_short": 4, "end_eid_short": 5, "text_short": "태권도 명예", "weight": 0.006}, 
            {"id": 57, "sent_id": 6, "start_eid": 19, "end_eid": 19, "ne_id": -1, "text": "명예", "start_eid_short": 19, "end_eid_short": 19, "text_short": "명예", "weight": 0.01}
        ]}, 
        {"id": 5, "type": "CV_POSITION", "number": "singular", "gender": "", "person": "", "animacy": "", "loc": "", "mention": [
            {"id": 50, "sent_id": 6, "start_eid": 11, "end_eid": 18, "ne_id": 5, "text": "약자에 대한 관심과 따뜻한 인간미를 보여주는 프란치스코 교황", "start_eid_short": 17, "end_eid_short": 18, "text_short": "프란치스코 교황", "weight": 0.01}, 
            {"id": 31, "sent_id": 5, "start_eid": 6, "end_eid": 15, "ne_id": 4, "text": "평소 태권도 종주국인 우리나라 가톨릭에 대해 애정을 보여온 프란치스코 교황", "start_eid_short": 14, "end_eid_short": 15, "text_short": "프란치스코 교황", "weight": 0.01}
        ]}, 
        {"id": 6, "type": "PS_NAME", "number": "singular", "gender": "", "person": "", "animacy": "", "loc": "", "mention": [
            {"id": 47, "sent_id": 6, "start_eid": 8, "end_eid": 10, "ne_id": 3, "text": "박영길 이탈리아태권도협회 명예회장", "start_eid_short": 8, "end_eid_short": 10, "text_short": "박영길 이탈리아태권도협회 명예회장", "weight": 0.012}, 
            {"id": 48, "sent_id": 6, "start_eid": 8, "end_eid": 8, "ne_id": 1, "text": "박영길", "start_eid_short": 8, "end_eid_short": 8, "text_short": "박영길", "weight": 0.007}
        ]}, 
        {"id": 7, "type": "QT_ORDER", "number": "singular", "gender": "", "person": "", "animacy": "", "loc": "", "mention": [
            {"id": 44, "sent_id": 6, "start_eid": 4, "end_eid": 4, "ne_id": 0, "text": "'태권", "start_eid_short": 4, "end_eid_short": 4, "text_short": "'태권", "weight": 0.058}, 
            {"id": 0, "sent_id": 0, "start_eid": 0, "end_eid": 0, "ne_id": 0, "text": "[오!클릭]", "start_eid_short": 0, "end_eid_short": 0, "text_short": "[오!클릭]", "weight": 0.048}, 
            {"id": 4, "sent_id": 0, "start_eid": 3, "end_eid": 3, "ne_id": 3, "text": "'태권", "start_eid_short": 3, "end_eid_short": 3, "text_short": "'태권", "weight": 0.052}, 
            {"id": 26, "sent_id": 4, "start_eid": 4, "end_eid": 4, "ne_id": 5, "text": "태권도", "start_eid_short": 4, "end_eid_short": 4, "text_short": "태권도", "weight": 0.031}, 
            {"id": 33, "sent_id": 5, "start_eid": 6, "end_eid": 7, "ne_id": 1, "text": "평소 태권도", "start_eid_short": 6, "end_eid_short": 7, "text_short": "평소 태권도", "weight": 0.0045}, 
            {"id": 18, "sent_id": 3, "start_eid": 5, "end_eid": 5, "ne_id": 2, "text": "'태권", "start_eid_short": 5, "end_eid_short": 5, "text_short": "'태권", "weight": 0.058}, 
            {"id": 9, "sent_id": 1, "start_eid": 3, "end_eid": 3, "ne_id": 1, "text": "태권도", "start_eid_short": 3, "end_eid_short": 3, "text_short": "태권도", "weight": 0.025}, 
            {"id": 29, "sent_id": 5, "start_eid": 0, "end_eid": 0, "ne_id": 0, "text": "태권도", "start_eid_short": 0, "end_eid_short": 0, "text_short": "태권도", "weight": 0.031}, 
            {"id": 60, "sent_id": 7, "start_eid": 1, "end_eid": 1, "ne_id": -1, "text": "'나무", "start_eid_short": 1, "end_eid_short": 1, "text_short": "'나무", "weight": 0.028}, 
            {"id": 63, "sent_id": 7, "start_eid": 9, "end_eid": 9, "ne_id": 1, "text": "'10단", "start_eid_short": 9, "end_eid_short": 9, "text_short": "'10단", "weight": 0.052}
        ]}
    ]
}